imsconvert/__init__.py
imsconvert/cliops.py
imsconvert/main.py
imsconvert/reader.py
imsconvert/writer.py
imsconvert-1.0.0.dist-info/METADATA
imsconvert-1.0.0.dist-info/WHEEL
imsconvert-1.0.0.dist-info/entry_points.txt
imsconvert-1.0.0.dist-info/top_level.txt
imsconvert-1.0.0.dist-info/RECORD
