Metadata-Version: 2.1
Name: imsconvert
Version: 1.0.0
Summary: For converting IMS structures to XML
Home-page: https://pypi.org/project/imsconvert/
Author: Jean Fecteau
Author-email: jfecteau@mbfbioscience.com
Keywords: sparc,mbf,bioscience,imaris
Requires-Python: >=3.6
Requires-Dist: h5py
Requires-Dist: vtk
Requires-Dist: numpy
